[
    {
        "transactionName": "UC03_TR01_mainpage_open",
        "rawStartTime": 1598270759224,
        "rawEndTime": 1598270766029
    },
    {
        "transactionName": "UC03_TR02_signupdata_post",
        "rawStartTime": 1598270766032,
        "rawEndTime": 1598270766756
    },
    {
        "transactionName": "UC03_TR03_successpage_open",
        "rawStartTime": 1598270766759,
        "rawEndTime": 1598270768607
    },
    {
        "transactionName": "UC03_TR04_DB_PosgreSQL",
        "rawStartTime": 1598270768609,
        "rawEndTime": 1598270769121
    }
]